{
  "codes": [
    {
      "id": "الصفحه الرئيسيه",
      "code": "0001"
    },
    {
      "id": "الصفحة الرئيسية",
      "code": "0001"
    },
    {
      "id": "الصفحه الرئيسية",
      "code": "0001"
    },
    {
      "id": "الصفحة الرئيسيه",
      "code": "0001"
    },
    {
      "id": "main page",
      "code": "0001"
    },
    {
      "id": "main",
      "code": "0001"
    },
    {
      "id": "home page",
      "code": "0001"
    },
    {
      "id": "home",
      "code": "0001"
    },
    {
      "id": "اي فواتيركم",
      "code": "0002"
    },
    {
      "id": "فواتيركم",
      "code": "0002"
    },
    {
      "id": "فواتير",
      "code": "0002"
    },
    {
      "id": "فاتوره",
      "code": "0002"
    },
    {
      "id": "فاتورة",
      "code": "0002"
    },
    {
      "id": "تسديد فاتورة",
      "code": "0002"
    },
    {
      "id": "تسديد الفاتورة",
      "code": "0002"
    },
    {
      "id": "تسديد الفواتير",
      "code": "0002"
    },
    {
      "id": "تسديد فواتير",
      "code": "0002"
    },
    {
      "id": "efawateercom",
      "code": "0002"
    },
    {
      "id": "efawateer",
      "code": "0002"
    },
    {
      "id": "fawateercom",
      "code": "0002"
    },
    {
      "id": "fawateer",
      "code": "0002"
    },
    {
      "id": "bill",
      "code": "0002"
    },
    {
      "id": "bills",
      "code": "0002"
    },
    {
      "id": "نقاط",
      "code": "0003"
    },
    {
      "id": "نقاطي",
      "code": "0003"
    },
    {
      "id": "نقاط العربي",
      "code": "0003"
    },
    {
      "id": "نقاط عربي",
      "code": "0003"
    },
    {
      "id": "نقاط العرب",
      "code": "0003"
    },
    {
      "id": "نقاطي العربي",
      "code": "0003"
    },
    {
      "id": "نقاطي العرب",
      "code": "0003"
    },
    {
      "id": "arabi points",
      "code": "0003"
    },
    {
      "id": "arabi point",
      "code": "0003"
    },
    {
      "id": "points",
      "code": "0003"
    },
    {
      "id": "point",
      "code": "0003"
    },
    {
      "id": "المدفوعات",
      "code": "0005"
    },
    {
      "id": "مدفوعات",
      "code": "0005"
    },
    {
      "id": "مدفوعاتكو",
      "code": "0005"
    },
    {
      "id": "مدفوع",
      "code": "0005"
    },
    {
      "id": "payment",
      "code": "0005"
    },
    {
      "id": "payments",
      "code": "0005"
    },
    {
      "id": "مدفوعاتكم",
      "code": "0005"
    },
    {
      "id": "مستقبليه",
      "code": "0006"
    },
    {
      "id": "مستقبلية",
      "code": "0006"
    },
    {
      "id": "متكرره",
      "code": "0006"
    },
    {
      "id": "متكرر",
      "code": "0006"
    },
    {
      "id": "متكررى",
      "code": "0006"
    },
    {
      "id": "حوالات مستقبليه",
      "code": "0006"
    },
    {
      "id": "حوالات مستقبلية",
      "code": "0006"
    },
    {
      "id": "حوالات متكرره",
      "code": "0006"
    },
    {
      "id": "حوالات متكرر",
      "code": "0006"
    },
    {
      "id": "حوالات متكررى",
      "code": "0006"
    },
    {
      "id": "حواله مستقبليه",
      "code": "0006"
    },
    {
      "id": "حواله مستقبلية",
      "code": "0006"
    },
    {
      "id": "حواله متكرره",
      "code": "0006"
    },
    {
      "id": "حواله متكرر",
      "code": "0006"
    },
    {
      "id": "حواله متكررى",
      "code": "0006"
    },
    {
      "id": "حواله المستقبليه",
      "code": "0006"
    },
    {
      "id": "حواله المستقبلية",
      "code": "0006"
    },
    {
      "id": "حواله المتكرره",
      "code": "0006"
    },
    {
      "id": "حواله المتكرر",
      "code": "0006"
    },
    {
      "id": "حواله المتكررى",
      "code": "0006"
    },
    {
      "id": "scheduled transfers",
      "code": "0006"
    },
    {
      "id": "scheduled transfer",
      "code": "0006"
    },
    {
      "id": "transfers",
      "code": "0006"
    },
    {
      "id": "transfer",
      "code": "0006"
    },
    {
      "id": "اداره المستفيدين",
      "code": "0007"
    },
    {
      "id": "المستفيدين",
      "code": "0007"
    },
    {
      "id": "مستفيدين",
      "code": "0007"
    },
    {
      "id": "ادارة المستفيدين",
      "code": "0007"
    },
    {
      "id": "اداره مستفيدين",
      "code": "0007"
    },
    {
      "id": "ادارة مستفيدين",
      "code": "0007"
    },
    {
      "id": "beneficiary management",
      "code": "0007"
    },
    {
      "id": "beneficiary",
      "code": "0007"
    },
    {
      "id": "jomopay",
      "code": "0008"
    },
    {
      "id": "jo mobile",
      "code": "0008"
    },
    {
      "id": "mopay",
      "code": "0008"
    },
    {
      "id": "جوموباي",
      "code": "0008"
    },
    {
      "id": "جوموبي",
      "code": "0008"
    },
    {
      "id": "خدمات حكوميه",
      "code": "0008"
    },
    {
      "id": "electronic deposit",
      "code": "0009"
    },
    {
      "id": "deposit",
      "code": "0009"
    },
    {
      "id": "electronic deposits",
      "code": "0009"
    },
    {
      "id": "deposits",
      "code": "0009"
    },
    {
      "id": "الخدمات الحكوميه",
      "code": "0008"
    },
    {
      "id": "جومبي",
      "code": "0008"
    },
    {
      "id": "جو موبايل",
      "code": "0008"
    },
    {
      "id": "جومباي",
      "code": "0008"
    },
    {
      "id": "الودائع الالكترونيه",
      "code": "0009"
    },
    {
      "id": "debit cards",
      "code": "0010"
    },
    {
      "id": "debit card",
      "code": "0010"
    },
    {
      "id": "debit",
      "code": "0010"
    },
    {
      "id": "الودائع الالكترونية",
      "code": "0009"
    },
    {
      "id": "ودائع الكترونيه",
      "code": "0009"
    },
    {
      "id": "وديعه",
      "code": "0009"
    },
    {
      "id": "وديعه الكترونيه",
      "code": "0009"
    },
    {
      "id": "وديعه الكترونية",
      "code": "0009"
    },
    {
      "id": "الوديعه",
      "code": "0009"
    },
    {
      "id": "الودائع الكترونية",
      "code": "0009"
    },
    {
      "id": "الودائع الكترونيه",
      "code": "0009"
    },
    {
      "id": "ودائع الكترونية",
      "code": "0009"
    },
    {
      "id": "بطاقات الدفع",
      "code": "0010"
    },
    {
      "id": "بطاقات دفع",
      "code": "0010"
    },
    {
      "id": "بطاقات",
      "code": "0010"
    },
    {
      "id": "بطاقه",
      "code": "0010"
    },
    {
      "id": "بطاقة",
      "code": "0010"
    },
    {
      "id": "البريد الالكتروني",
      "code": "0011"
    },
    {
      "id": "secure mail",
      "code": "0011"
    },
    {
      "id": "mail",
      "code": "0011"
    },
    {
      "id": "البريد",
      "code": "0011"
    },
    {
      "id": "بريد الالكتروني",
      "code": "0011"
    },
    {
      "id": "البريد الكتروني",
      "code": "0011"
    },
    {
      "id": "بريد الكتروني",
      "code": "0011"
    },
    {
      "id": "اتصل بنا",
      "code": "0012"
    },
    {
      "id": "contact us",
      "code": "0012"
    },
    {
      "id": "contact",
      "code": "0012"
    },
    {
      "id": "اتصل بنى",
      "code": "0012"
    },
    {
      "id": "اتصل",
      "code": "0012"
    },
    {
      "id": "اتصال",
      "code": "0012"
    },
    {
      "id": "المواقع",
      "code": "0013"
    },
    {
      "id": "location",
      "code": "0013"
    },
    {
      "id": "locations",
      "code": "0013"
    },
    {
      "id": "مواقع",
      "code": "0013"
    },
    {
      "id": "الموقع",
      "code": "0013"
    },
    {
      "id": "موقع",
      "code": "0013"
    },
    {
      "id": "المنتجات",
      "code": "0014"
    },
    {
      "id": "products",
      "code": "0014"
    },
    {
      "id": "product",
      "code": "0014"
    },
    {
      "id": "منتجات",
      "code": "0014"
    },
    {
      "id": "المنتج",
      "code": "0014"
    },
    {
      "id": "منتج",
      "code": "0014"
    },
    {
      "id": "العروض",
      "code": "0015"
    },
    {
      "id": "عروض",
      "code": "0015"
    },
    {
      "id": "عرض",
      "code": "0015"
    },
    {
      "id": "offers",
      "code": "0015"
    },
    {
      "id": "offer",
      "code": "0015"
    },
    {
      "id": "العرض",
      "code": "0015"
    },
    {
      "id": "الادوات",
      "code": "0016"
    },
    {
      "id": "tool",
      "code": "0016"
    },
    {
      "id": "tools",
      "code": "0016"
    },
    {
      "id": "ادوات",
      "code": "0016"
    },
    {
      "id": "أدوات",
      "code": "0016"
    },
    {
      "id": "الأدوات",
      "code": "0016"
    },
    {
      "id": "اعدادات",
      "code": "0017"
    },
    {
      "id": "الاعدادات",
      "code": "0017"
    },
    {
      "id": "اعداد",
      "code": "0017"
    },
    {
      "id": "setting",
      "code": "0017"
    },
    {
      "id": "settings",
      "code": "0017"
    },
    {
      "id": "الاعداد",
      "code": "0017"
    },
    {
      "id": "تسجيل الخروج",
      "code": "0018"
    },
    {
      "id": "تسجيل خروج",
      "code": "0018"
    },
    {
      "id": "خروج",
      "code": "0018"
    },
    {
      "id": "الخروج",
      "code": "0018"
    },
    {
      "id": "log out",
      "code": "0018"
    },
    {
      "id": "بين حساباتي",
      "code": "0019"
    },
    {
      "id": "بين الحسابات",
      "code": "0019"
    },
    {
      "id": "own accounts",
      "code": "0019"
    },
    {
      "id": "own account",
      "code": "0019"
    },
    {
      "id": "حواله بين حساباتي",
      "code": "0019"
    },
    {
      "id": "حواله بين الحسابات",
      "code": "0019"
    },
    {
      "id": "حوالة بين حساباتي",
      "code": "0019"
    },
    {
      "id": "حوالة بين الحسابات",
      "code": "0019"
    },
    {
      "id": "within arab bank",
      "code": "0020"
    },
    {
      "id": "with in arab bank",
      "code": "0020"
    },
    {
      "id": "within arabbank",
      "code": "0020"
    },
    {
      "id": "with in arabbank",
      "code": "0020"
    },
    {
      "id": "داخل البنك العربي",
      "code": "0020"
    },
    {
      "id": "داخل البنك العرب",
      "code": "0020"
    },
    {
      "id": "داخل بنك العرب",
      "code": "0020"
    },
    {
      "id": "داخل بنك العربي",
      "code": "0020"
    },
    {
      "id": "داخل البنك",
      "code": "0020"
    },
    {
      "id": "حواله داخل البنك العربي",
      "code": "0020"
    },
    {
      "id": "حواله داخل البنك العرب",
      "code": "0020"
    },
    {
      "id": "حواله داخل بنك العرب",
      "code": "0020"
    },
    {
      "id": "حواله داخل بنك العربي",
      "code": "0020"
    },
    {
      "id": "حواله داخل البنك",
      "code": "0020"
    },
    {
      "id": "حوالة داخل البنك العربي",
      "code": "0020"
    },
    {
      "id": "حوالة داخل البنك العرب",
      "code": "0020"
    },
    {
      "id": "حوالة داخل بنك العرب",
      "code": "0020"
    },
    {
      "id": "حوالة داخل بنك العربي",
      "code": "0020"
    },
    {
      "id": "حوالة داخل البنك",
      "code": "0020"
    },
    {
      "id": "محليه",
      "code": "0021"
    },
    {
      "id": "domestic",
      "code": "0021"
    },
    {
      "id": "domestics",
      "code": "0021"
    },
    {
      "id": "محلية",
      "code": "0021"
    },
    {
      "id": "حواله محليه",
      "code": "0021"
    },
    {
      "id": "حوالة محليه",
      "code": "0021"
    },
    {
      "id": "حواله محلية",
      "code": "0021"
    },
    {
      "id": "حوالة محلية",
      "code": "0021"
    },
    {
      "id": "المحليه",
      "code": "0021"
    },
    {
      "id": "المحلية",
      "code": "0021"
    },
    {
      "id": "الحواله محليه",
      "code": "0021"
    },
    {
      "id": "الحوالة محليه",
      "code": "0021"
    },
    {
      "id": "الحواله محلية",
      "code": "0021"
    },
    {
      "id": "الحوالة محلية",
      "code": "0021"
    },
    {
      "id": "خارجيه",
      "code": "0022"
    },
    {
      "id": "خارجية",
      "code": "0022"
    },
    {
      "id": "abroad",
      "code": "0022"
    },
    {
      "id": "حواله خارجيه",
      "code": "0022"
    },
    {
      "id": "حوالة خارجيه",
      "code": "0022"
    },
    {
      "id": "حواله خارجية",
      "code": "0022"
    },
    {
      "id": "حوالة خارجية",
      "code": "0022"
    },
    {
      "id": "الخارجيه",
      "code": "0022"
    },
    {
      "id": "الخارجية",
      "code": "0022"
    },
    {
      "id": "الحواله الخارجيه",
      "code": "0022"
    },
    {
      "id": "الحوالة الخارجيه",
      "code": "0022"
    },
    {
      "id": "الحواله الخارجية",
      "code": "0022"
    },
    {
      "id": "الحوالة الخارجيه",
      "code": "0022"
    },
    {
      "id": "حواله الخارجيه",
      "code": "0022"
    },
    {
      "id": "حوالة الخارجيه",
      "code": "0022"
    },
    {
      "id": "حواله الخارجية",
      "code": "0022"
    },
    {
      "id": "حوالة الخارجيه",
      "code": "0022"
    },
    {
      "id": "الحسابات",
      "code": "0023"
    },
    {
      "id": "حسابات",
      "code": "0023"
    },
    {
      "id": "حساباتي",
      "code": "0023"
    },
    {
      "id": "accounts",
      "code": "0023"
    },
    {
      "id": "account",
      "code": "0023"
    },
    {
      "id": "القروض",
      "code": "0024"
    },
    {
      "id": "loan",
      "code": "0024"
    },
    {
      "id": "loans",
      "code": "0024"
    },
    {
      "id": "قروض",
      "code": "0024"
    },
    {
      "id": "قرض",
      "code": "0024"
    },
    {
      "id": "القرض",
      "code": "0024"
    }
  ]
}